pyvista/__init__.py
pyvista/apo_inst.py
pyvista/apogee.py
pyvista/arces.py
pyvista/bitmask.py
pyvista/boss.py
pyvista/centroid.py
pyvista/cmap.py
pyvista/dataclass.py
pyvista/etc.py
pyvista/gaia.py
pyvista/image.py
pyvista/imred.py
pyvista/look.py
pyvista/mmm.py
pyvista/reduce.py
pyvista/refcorr.py
pyvista/sdss.py
pyvista/ser_reader.py
pyvista/simulate.py
pyvista/skycalc.py
pyvista/slitmask.py
pyvista/spectra.py
pyvista/stars.py
pyvista/tv.py
pyvista/utils.py
pyvista/data/landolt82.stn
pyvista/data/APOGEE/APOGEE.yml
pyvista/data/APOGEE/APOGEE_trace.fits
pyvista/data/APOGEES/APOGEES.yml
pyvista/data/ARCES/ARCES.yml
pyvista/data/ARCES/ARCES_mask.fits
pyvista/data/ARCES/ARCES_traces.fits
pyvista/data/ARCES/ARCES_wave.fits
pyvista/data/ARCES/traces
pyvista/data/ARCTIC/ARCTIC.yml
pyvista/data/ARCTIC/ARCTICquad.yml
pyvista/data/BOSS/BOSS.yml
pyvista/data/BOSS/BOSS_b.fits
pyvista/data/BOSS/BOSS_b1_trace.fit
pyvista/data/BOSS/BOSS_b1_waves.fits
pyvista/data/BOSS/BOSS_b2_trace.fit
pyvista/data/BOSS/BOSS_b2_waves.fits
pyvista/data/BOSS/BOSS_r.fits
pyvista/data/BOSS/BOSS_r1_trace.fit
pyvista/data/BOSS/BOSS_r1_waves.fits
pyvista/data/BOSS/BOSS_r2_trace.fit
pyvista/data/BOSS/BOSS_r2_waves.fits
pyvista/data/BOSS/boss.txt
pyvista/data/DIS/DIS.yml
pyvista/data/DIS/DIS_blue_trace.fits
pyvista/data/DIS/DIS_blue_waves.fits
pyvista/data/DIS/DIS_hires_6400_waves.pkl
pyvista/data/DIS/DIS_hires_6400_waves.pkl.old
pyvista/data/DIS/DIS_hires_blue_waves.pkl
pyvista/data/DIS/DIS_hires_red_6400_waves.pkl
pyvista/data/DIS/DIS_lowres_waves.pkl
pyvista/data/DIS/DIS_lowres_waves.pkl.old
pyvista/data/DIS/DIS_mask.fits
pyvista/data/DIS/DIS_red_trace.fits
pyvista/data/DIS/DIS_red_waves.fits
pyvista/data/DIS/DIS_traces.pkl
pyvista/data/DIS/DIS_traces.pkl.old
pyvista/data/KOSMOS/KOSMOS.yml
pyvista/data/KOSMOS/KOSMOS_blue_cent_waves.fits
pyvista/data/KOSMOS/KOSMOS_blue_high_waves.fits
pyvista/data/KOSMOS/KOSMOS_blue_low_waves.fits
pyvista/data/KOSMOS/KOSMOS_blue_waves.fits
astro_pyvista-0.4.2.dist-info/LICENSE
astro_pyvista-0.4.2.dist-info/METADATA
astro_pyvista-0.4.2.dist-info/WHEEL
astro_pyvista-0.4.2.dist-info/top_level.txt
astro_pyvista-0.4.2.dist-info/RECORD
