Metadata-Version: 2.1
Name: astro-pyvista
Version: 0.4.2
Summary: Astronomical image processing
Author-email: Jon Holtzman <holtzmanjon@gmail.com>
Project-URL: Homepage, https://github.com/holtzmanjon/pyvista
Classifier: Development Status :: 1 - Planning
Classifier: Intended Audience :: Science/Research
Classifier: License :: OSI Approved :: BSD License
Classifier: Operating System :: OS Independent
Classifier: Programming Language :: Python :: 3
Requires-Python: >=3.9
License-File: LICENSE
Requires-Dist: ipython
Requires-Dist: jupyter
Requires-Dist: holtz-tools
Requires-Dist: astropy
Requires-Dist: astroscrappy
Requires-Dist: gaiaxpy
Requires-Dist: photutils
Requires-Dist: astroplan
Requires-Dist: pyyaml
Requires-Dist: pyautogui
Requires-Dist: pydl
Requires-Dist: astroquery
Requires-Dist: importlib-resources
Requires-Dist: sphinx
Requires-Dist: numpy
Requires-Dist: matplotlib
Requires-Dist: scipy
Requires-Dist: scikit-learn
Requires-Dist: scikit-image
Requires-Dist: esutil
Requires-Dist: imageio
Requires-Dist: imageio-ffmpeg
